{
  "intimacoes": [
    {
      "contexto": "# Dados do Processo \r\n\r\n## Informações Básicas do Processo\r\n\r\n- **Classe Processual**: Cumprimento de sentença  \r\n- **Comarca**: Coronel Bicaco  \r\n- **Competência**: Cível - Geral  \r\n- **Data Ajuizamento**: 23/09/2024  \r\n- **Assuntos**: Honorários Advocatícios / Sucumbência  \r\n- **Valor da Causa**: R$ 555,01  \r\n- **Órgão Julgador**: Juízo do Juizado Especial Cível Adjunto da Comarca de Coronel Bicaco  \r\n- **Magistrados**: 00518215407, 31454231424, 73054013073  \r\n- **Processo Físico**: Não  \r\n- **Prioridades**: Justiça Gratuita - Requerida  \r\n\r\n## Dados da Intimação\r\n\r\n- **Processo**: 5001374-79.2024.8.21.0093  \r\n- **Grau**: 1º Grau  \r\n- **Tipo Comunicação**: INT  \r\n- **Origem**: EPROC 1º Grau  \r\n- **Status**: Finalizada  \r\n- **Urgente**: Não  \r\n- **Classe**: Cumprimento de sentença  \r\n- **Intimados**:  \r\n  - ALTIVA COSTA DE SOUZA (Polo Ativo)  \r\n- **Dias**: 10 dias  \r\n- **Eventos Relacionados**: 15  \r\n\r\n## Movimentações Processuais Recentes\r\n\r\n### Movimentação 15\r\n- **Data/Hora**: 28/07/2025 20:36:24\r\n- **Documentos Vinculados**: 1 documentos\r\n\r\n## Textos dos Documentos\r\n\r\n### Documento 1\r\n```\r\n\r\nPoder Judiciário\r\nTribunal de Justiça do Estado do Rio Grande do Sul\r\nJuizado Especial Cível Adjunto da Comarca de Coronel Bicaco\r\nRua Francisco Manoel Diniz, 706 - Bairro: Centro - CEP: 98580000 - Fone: (55) 3029-9955 - Email: frcelbicacvjud@tjrs.jus.br\r\n\r\n\r\nCUMPRIMENTO DE SENTENÇA Nº 5001374-79.2024.8.21.0093/RS\r\n\r\nEXEQUENTE: ALTIVA COSTA DE SOUZA\r\n\r\nEXECUTADO: ESTADO DO RIO GRANDE DO SUL\r\n\r\nDESPACHO/DECISÃO\r\n\r\n1. Trata-se de cumprimento de sentença de honorários sucumbenciais à FADEP, proposto pela Defensoria Pública.\r\n\r\n2. O executado se insurgiu ao cálculo apresentado pela parte exequente, sustentando que descabe a fixação de honorários de 10% no cumprimento contra Fazenda Pública, diante da incidência do Tema 1.190 do STJ.\r\n\r\nAssim sendo, expeça-se RPV em favor do Fundo de Aparelhamento da Defensoria Pública, para pagamento dos honorários sucumbenciais estabelecidos na fase de conhecimento, no montante de R$ 504,55.\r\n\r\nIntimem-se as partes da sua expedição.\r\n\r\nCom o pagamento, expeça(m)-se o(s) respectivo(s) alvará(s) em favor da exequente, na conta FADEP.\r\n\r\nCumpra-se com urgência/prioridade.\r\n\r\nApós, intime-se a parte autora para que diga sobre o prosseguimento da lide, sob pena de aquiescer tacitamente com o pagamento do débito e, assim, com a consequente extinção do feito.\r\n\r\nEm nada sendo requerido, arquive-se com baixa.\r\n\r\n\r\nDocumento assinado eletronicamente por EZEQUIELA BASSO BERNARDI, Juíza de Direito, em 28/07/2025, às 20:36:24.\r\n\r\n5001374-79.2024.8.21.0093",
      "classificacao_manual": "RENUNCIAR PRAZO",
      "informacoes_adicionais": "a intimação é da primeira parte da decisão, que determina a expedição de RPV como pedimos",
      "processo": "5001374-79.2024.8.21.0093",
      "orgao_julgador": "Juízo do Juizado Especial Cível Adjunto da Comarca de Coronel Bicaco",
      "classe": "Cumprimento de sentença",
      "disponibilizacao": "28/07/2025",
      "intimado": "ALTIVA COSTA DE SOUZA",
      "status": "Finalizada",
      "prazo": "10 dias",
      "data_criacao": "2025-08-19T18:20:10.572235",
      "analises": [],
      "id": "bf0610d8-e158-4bcb-a6d6-9fc0fba33fb8"
    },
    {
      "contexto": "# Dados do Processo\r\n\r\n## Informações Básicas do Processo\r\n\r\n- **Classe Processual**: Cumprimento de sentença\r\n- **Comarca**: Carazinho\r\n- **Competência**: Cível - Geral\r\n- **Data Ajuizamento**: 2025-07-18T14:18:56\r\n- **Assuntos**: Sucumbência \r\n- **Valor da Causa**: R$ 406,61\r\n- **Órgão Julgador**: Juízo da 2ª Vara Cível da Comarca de Carazinho\r\n- **Magistrados**: 00518215407, 31454231424, 73054013073\r\n- **Processo Físico**: Não\r\n- **Prioridades**: Justiça Gratuita - Requerida\r\n\r\n## Dados da Intimação\r\n\r\n- **Processo**: 50072045020258210009\r\n- **Grau**: P\r\n- **Tipo Comunicação**: INT\r\n- **Origem**: EPROC1G\r\n- **Status**: prazo_em_curso\r\n- **Urgente**: Não\r\n- **Classe**: Cumprimento de sentença\r\n- **Intimados**: \r\n  - LUIZ ROMARIO LOPES DA SILVA (AT)\r\n- **Dias**: 30 dias\r\n- **Responsáveis na Defensoria**: 4214960 \r\n- **Eventos Relacionados**: 3\r\n\r\n## Movimentações Processuais Recentes\r\n\r\n### Movimentação 3\r\n- **Data/Hora**: 2025-07-28T11:12:01\r\n- **Documentos Vinculados**: 1 documentos\r\n\r\n## Textos dos Documentos\r\n\r\n### Documento 1\r\n```\r\nPoder Judiciário\r\nTribunal de Justiça do Estado do Rio Grande do Sul\r\n2ª Vara Cível da Comarca de Carazinho\r\n\r\nCUMPRIMENTO DE SENTENÇA Nº 5007204-50.2025.8.21.0009/RS\r\n\r\nEXEQUENTE: LUIZ ROMARIO LOPES DA SILVA\r\n\r\nEXECUTADO: FACTA FINANCEIRA S.A. CREDITO, FINANCIAMENTO E INVESTIMENTO\r\n\r\nDESPACHO/DECISÃO\r\n\r\n1. Estendi e anotei o benefício da gratuidade judiciária à autora para esta fase processual. \r\n\r\n2. Trata-se de cumprimento de sentença relativo aos honorários fixados em favor do Fundo de Aparelhamento da Defensoria Pública (FADEP) originário dos autos vinculados a este feito.\r\n\r\n3. Na forma do artigo 513, § 2º, do Código de Processo Civil, intime(m)-se o(s) executado(s) para que, no prazo de 15 (quinze) dias, pague(em) o valor indicado no demonstrativo discriminado e atualizado do crédito, acrescido de custas, se houver.\r\n\r\nFica(m) o(s) executado(s) advertido(s) de que, transcorrido o prazo previsto no artigo 523 sem o pagamento voluntário , inicia-se o prazo de 15 (quinze) dias para que, independentemente de penhora ou nova intimação, apresente(m), nos próprios autos, sua impugnação.\r\n\r\n4. Não ocorrendo pagamento voluntário no prazo do artigo 523 do Código de Processo Civil, o débito será acrescido de multa de 10% e, também, de honorários de advogado de 10%.\r\n\r\n5. Comprovado o pagamento voluntário, libere-se a quantia depositada em favor do FADEP, mediante expedição de alvará, e, nada mais pedido, retornem os autos conclusos para extinção.\r\n\r\nDocumento assinado eletronicamente por ABEL DOS SANTOS RODRIGUES, Juiz de Direito, em 28/07/2025, às 13:51:43.\r\n```",
      "classificacao_manual": "RENUNCIAR PRAZO",
      "informacoes_adicionais": "Decisão que recebe a fase de cumprimento de sentença.",
      "processo": "50072045020258210009",
      "orgao_julgador": "Juízo da 2ª Vara Cível da Comarca de Carazinho",
      "classe": "Cumprimento de sentença",
      "disponibilizacao": null,
      "intimado": "LUIZ ROMARIO LOPES DA SILVA",
      "status": "prazo_em_curso",
      "prazo": "30 dias",
      "data_criacao": "2025-08-11T19:43:00.173097",
      "analises": [],
      "id": "6eb3136c-38e6-472e-8928-3ab82e9230dd"
    },
    {
      "contexto": "# Dados do Processo \r\n\r\n## Informações Básicas do Processo\r\n\r\n- **Classe Processual**: Cumprimento de Sentença contra a Fazenda Pública  \r\n- **Comarca**: Teutônia  \r\n- **Competência**: Cível JIJ  \r\n- **Data Ajuizamento**: 25/07/2025  \r\n- **Assuntos**: Sucumbência  \r\n- **Valor da Causa**: R$ 700,00  \r\n- **Órgão Julgador**: Juízo da 2ª Vara Judicial da Comarca de Teutônia  \r\n- **Magistrados**: 00518215407, 31454231424, 73054013073  \r\n- **Processo Físico**: Não  \r\n- **Prioridades**: Justiça Gratuita - Requerida  \r\n\r\n## Dados da Intimação\r\n\r\n- **Processo**: 5003885-12.2025.8.21.0159  \r\n- **Grau**: 1º Grau  \r\n- **Tipo Comunicação**: INT  \r\n- **Origem**: EPROC 1º Grau  \r\n- **Status**: Finalizada  \r\n- **Urgente**: Não  \r\n- **Classe**: Cumprimento de Sentença contra a Fazenda Pública  \r\n- **Intimados**:  \r\n  - VALENTINA GONCALVES DO PRADO (Polo Ativo)  \r\n- **Dias**: 15 dias  \r\n- **Eventos Relacionados**: 3  \r\n\r\n## Movimentações Processuais Recentes\r\n\r\n- **28/07/2025 18:53:55** – Proferido despacho de mero expediente, movimentado por: Patricia Stelmar Netto - Magistrado (Despacho/decisão)  \r\n- **28/07/2025 18:53:55** – Expedido/certificada a intimação eletrônica - Referente ao Evento 3  \r\n\r\n## Textos dos Documentos\r\n\r\n### Documento 1\r\n```\r\n\r\nPoder Judiciário\r\nTribunal de Justiça do Estado do Rio Grande do Sul\r\n2ª Vara Judicial da Comarca de Teutônia\r\nAv. 01 - Norte, 200 - Bairro: Languiru - CEP: 95890000 - Fone: (51)3098--5592 - Email: frteutonia2vjud@tjrs.jus.br\r\n\r\n\r\nCUMPRIMENTO DE SENTENÇA CONTRA A FAZENDA PÚBLICA Nº 5003885-12.2025.8.21.0159/RS\r\n\r\nDESPACHO/DECISÃO\r\n\r\nVistos..\r\n\r\n \r\n\r\nÀ DPE para verificar o tombamento/cadastramento do processo, já que a inicial está nominada em JESSICA GONCALVES DE MORAIS, porém foi cadastrado no sistema como VALENTINA GONCALVES DO PRADO\r\n\r\nDL.\r\n\r\n\r\nDocumento assinado eletronicamente por PATRICIA STELMAR NETTO, Juíza de Direito, em 28/07/2025, às 18:53:55, conforme art. 1º, III, \"b\", da Lei 11.419/2006. A autenticidade do documento pode ser conferida no site https://eproc1g.tjrs.jus.br/eproc/externo_controlador.php?acao=consulta_autenticidade_documentos, informando o código verificador 10087585259v2 e o código CRC 6ae9ecdf.\r\n\r\n \r\n\r\n \r\n\r\n5003885-12.2025.8.21.0159\r\n```",
      "classificacao_manual": "ANALISAR PROCESSO",
      "informacoes_adicionais": "Verificar divergência entre nome na inicial (JESSICA) e cadastro no sistema (VALENTINA)",
      "processo": "5003885-12.2025.8.21.0159",
      "orgao_julgador": "Juízo da 2ª Vara Judicial da Comarca de Teutônia",
      "classe": "Cumprimento de Sentença contra a Fazenda Pública",
      "disponibilizacao": "28/07/2025",
      "intimado": "VALENTINA GONCALVES DO PRADO",
      "status": "Finalizada",
      "prazo": "15 dias",
      "data_criacao": "2025-08-22T18:55:07.729458",
      "analises": [],
      "id": "6eb3136c-38e6-472e-8928-3ab82e9230dd"
    }
  ]
}